README.md
pyproject.toml
my_project_name/__main__.py
my_project_name.egg-info/PKG-INFO
my_project_name.egg-info/SOURCES.txt
my_project_name.egg-info/dependency_links.txt
my_project_name.egg-info/top_level.txt