Metadata-Version: 2.1
Name: my-project-name
Version: 0.0.0
Summary: My project name
Author: Jacob Striebel
Project-URL: Homepage, https://github.com/striebel/python-project-stub
